QiongZuoluoDeLinuxShuFix1/README.md
QiongZuoluoDeLinuxShuFix1/__init__.py
QiongZuoluoDeLinuxShuFix1/__main__.py
QiongZuoluoDeLinuxShuFix1/file.epub
QiongZuoluoDeLinuxShuFix1/index.html
QiongZuoluoDeLinuxShuFix1/css/__init__.py
QiongZuoluoDeLinuxShuFix1/css/annotations.css
QiongZuoluoDeLinuxShuFix1/css/main.css
QiongZuoluoDeLinuxShuFix1/css/normalize.css
QiongZuoluoDeLinuxShuFix1/css/popup.css
QiongZuoluoDeLinuxShuFix1/font/__init__.py
QiongZuoluoDeLinuxShuFix1/font/fontello.eot
QiongZuoluoDeLinuxShuFix1/font/fontello.svg
QiongZuoluoDeLinuxShuFix1/font/fontello.ttf
QiongZuoluoDeLinuxShuFix1/font/fontello.woff
QiongZuoluoDeLinuxShuFix1/img/__init__.py
QiongZuoluoDeLinuxShuFix1/img/annotator-glyph-sprite.png
QiongZuoluoDeLinuxShuFix1/img/annotator-icon-sprite.png
QiongZuoluoDeLinuxShuFix1/img/apple-touch-icon.png
QiongZuoluoDeLinuxShuFix1/img/cancelfullscreen.png
QiongZuoluoDeLinuxShuFix1/img/close.png
QiongZuoluoDeLinuxShuFix1/img/fullscreen.png
QiongZuoluoDeLinuxShuFix1/img/loader.gif
QiongZuoluoDeLinuxShuFix1/img/menu-icon.png
QiongZuoluoDeLinuxShuFix1/img/save.png
QiongZuoluoDeLinuxShuFix1/img/saved.png
QiongZuoluoDeLinuxShuFix1/img/settings-s.png
QiongZuoluoDeLinuxShuFix1/img/settings.png
QiongZuoluoDeLinuxShuFix1/img/star.png
QiongZuoluoDeLinuxShuFix1/js/__init__.py
QiongZuoluoDeLinuxShuFix1/js/epub.js
QiongZuoluoDeLinuxShuFix1/js/epub.min.js
QiongZuoluoDeLinuxShuFix1/js/epub.min.map
QiongZuoluoDeLinuxShuFix1/js/hooks.min.js
QiongZuoluoDeLinuxShuFix1/js/hooks.min.map
QiongZuoluoDeLinuxShuFix1/js/reader.js
QiongZuoluoDeLinuxShuFix1/js/reader.js.map
QiongZuoluoDeLinuxShuFix1/js/reader.min.js
QiongZuoluoDeLinuxShuFix1/js/reader.min.map
QiongZuoluoDeLinuxShuFix1/js/hooks/__init__.py
QiongZuoluoDeLinuxShuFix1/js/hooks/extensions/__init__.py
QiongZuoluoDeLinuxShuFix1/js/hooks/extensions/highlight.js
QiongZuoluoDeLinuxShuFix1/js/libs/__init__.py
QiongZuoluoDeLinuxShuFix1/js/libs/jquery.min.js
QiongZuoluoDeLinuxShuFix1/js/libs/localforage.min.js
qiong_zuoluo_de_linux_shu_fix1-2025.3.25.1.dist-info/METADATA
qiong_zuoluo_de_linux_shu_fix1-2025.3.25.1.dist-info/WHEEL
qiong_zuoluo_de_linux_shu_fix1-2025.3.25.1.dist-info/entry_points.txt
qiong_zuoluo_de_linux_shu_fix1-2025.3.25.1.dist-info/top_level.txt
qiong_zuoluo_de_linux_shu_fix1-2025.3.25.1.dist-info/RECORD
